kama_telem_plugin/__init__.py
kama_telem_plugin/consts.py
kama_telem_plugin/nmachine_telem_backend.py
kama_telem_plugin/plugin.py
kama_telem_plugin/assets/delete-telem-storage-info.md
kama_telem_plugin/assets/enable-synopsis.md
kama_telem_plugin/assets/telem-detail-info.md
kama_telem_plugin/descriptors/operation/predicate-actions.yaml
kama_telem_plugin/descriptors/operation/disable/actions.yaml
kama_telem_plugin/descriptors/operation/disable/operation.yaml
kama_telem_plugin/descriptors/operation/enable/input.yaml
kama_telem_plugin/descriptors/operation/enable/operation.yaml
kama_telem_plugin/descriptors/utils/predicates.yaml
kama_telem_plugin/descriptors/utils/resource-existence-predicates.yaml
kama_telem_plugin/descriptors/utils/suppliers.yaml
kama_telem_plugin/descriptors/variables/dependencies.yaml
kama_telem_plugin/descriptors/variables/deployment.yaml
kama_telem_plugin/descriptors/variables/pvc.yaml
kama_telem_plugin/models/__init__.py
kama_telem_plugin/models/telem_state_helper.py
kama_telem_plugin-0.0.8.dist-info/METADATA
kama_telem_plugin-0.0.8.dist-info/WHEEL
kama_telem_plugin-0.0.8.dist-info/top_level.txt
kama_telem_plugin-0.0.8.dist-info/RECORD
